MANIFEST.in
README.md
setup.py
spotify/__init__.py
spotify/spotify.py
spotify_lite.egg-info/PKG-INFO
spotify_lite.egg-info/SOURCES.txt
spotify_lite.egg-info/dependency_links.txt
spotify_lite.egg-info/top_level.txt