Metadata-Version: 2.1
Name: spotify-lite
Version: 1.0.1
Summary: Lightweight, single-file, zero-dependency Spotify wrapper for Python 2.7+ and Python 3.x.
Home-page: https://github.com/orangeblock/spotify-lite
Author: orangeblock
Author-email: noreply@void.dev
License: MIT
Platform: UNKNOWN
Classifier: Intended Audience :: Developers
Classifier: Programming Language :: Python :: 2.7
Classifier: Programming Language :: Python :: 3
Classifier: License :: OSI Approved :: MIT License
Classifier: Topic :: Software Development :: Libraries :: Python Modules
